arospy/__init__.py
arospy/action.py
arospy/client.py
arospy/service.py
arospy/subscriber.py
arospy/timer.py
arospy_Hugal31-0.2.0.dist-info/LICENSE
arospy_Hugal31-0.2.0.dist-info/METADATA
arospy_Hugal31-0.2.0.dist-info/WHEEL
arospy_Hugal31-0.2.0.dist-info/top_level.txt
arospy_Hugal31-0.2.0.dist-info/RECORD
